FuxiShensuanAlibabaJingjitiHexinDiaoduXitongJiemiFix1/README.md
FuxiShensuanAlibabaJingjitiHexinDiaoduXitongJiemiFix1/__init__.py
FuxiShensuanAlibabaJingjitiHexinDiaoduXitongJiemiFix1/__main__.py
FuxiShensuanAlibabaJingjitiHexinDiaoduXitongJiemiFix1/file.pdf
FuxiShensuanAlibabaJingjitiHexinDiaoduXitongJiemiFix1/index.html
fuxi_shensuan_alibaba_jingjiti_hexin_diaodu_xitong_jiemi_fix1-2025.3.25.0.dist-info/METADATA
fuxi_shensuan_alibaba_jingjiti_hexin_diaodu_xitong_jiemi_fix1-2025.3.25.0.dist-info/WHEEL
fuxi_shensuan_alibaba_jingjiti_hexin_diaodu_xitong_jiemi_fix1-2025.3.25.0.dist-info/entry_points.txt
fuxi_shensuan_alibaba_jingjiti_hexin_diaodu_xitong_jiemi_fix1-2025.3.25.0.dist-info/top_level.txt
fuxi_shensuan_alibaba_jingjiti_hexin_diaodu_xitong_jiemi_fix1-2025.3.25.0.dist-info/RECORD
